etl/__init__.py
etl/__main__.py
etl/cli.py
etl/core.py
etl/monitor.py
etl/extract/__init__.py
etl/extract/collection.py
etl/extract/collection_map.py
etl/extract/extractor.py
etl/extract/init_mongo.py
etl/extract/notification.py
etl/extract/tailer.py
etl/extract/transfer.py
etl/extract/transfer_info.py
etl/load/__init__.py
etl/load/constraint.py
etl/load/init_pg.py
etl/load/procedure.py
etl/load/row.py
etl/load/schema.py
etl/load/table.py
etl/transform/__init__.py
etl/transform/config_parser.py
etl/transform/relation.py
etl/transform/type_checker.py
etl/transform/unnester.py
etl/transform/constants/__init__.py
tests/__init__.py
tests/extract/__init__.py
tests/extract/test_collection.py
tests/extract/test_collection_map.py
tests/extract/test_extractor.py
tests/extract/test_tailer.py
tests/extract/test_transfer_info.py
purrito-1.0.4.dist-info/LICENCE
purrito-1.0.4.dist-info/METADATA
purrito-1.0.4.dist-info/WHEEL
purrito-1.0.4.dist-info/entry_points.txt
purrito-1.0.4.dist-info/top_level.txt
purrito-1.0.4.dist-info/RECORD
