Metadata-Version: 2.1
Name: purrito
Version: 1.0.4
Summary: ETL tool for transfering data from MongoDB to PostgreSQL
Home-page: https://boosterfuels.github.io/purr
Author: Anett Balázsics
License: UNKNOWN
Platform: UNKNOWN
Classifier: Programming Language :: Python :: 3
Classifier: License :: OSI Approved :: MIT License
Classifier: Operating System :: OS Independent
Classifier: Topic :: Database
Requires-Dist: psycopg2 (==2.8)
Requires-Dist: pymongo (==3.6.1)
Requires-Dist: PyYAML (==3.12)
